sq0110.v
module sq0110 (x , clk , reset, z) ;
    input x , clk , reset ;
    output reg z ;

    reg [0:1] PS , NS ;
    parameter S0=0 , S1=1 , S2=2 , S3=3 ;

    always @(posedge clk or posedge reset)
        if(reset)
            PS <= S0 ;
        else
            PS <= NS ;

    always @(PS , x)
        case(PS)
            S0 : begin
                z <= x ? 0 : 0 ;
                NS <= x ? S0 : S1 ;
                end

            S1 : begin
                z <= x ? 0 : 0 ;
                NS <= x ? S2 : S1 ;
                end

            S2 : begin
                z <= x ? 0 : 0 ;
                NS <= x ? S3 : S1 ;
                end

            S3 : begin
                z <= x ? 0 : 1 ;
                NS <= x ? S0 : S1 ;
                end
        endcase

endmodule

tb_sq0110.v
`timescale 1ns/1ps
module tb_sq0110 ;

    reg x , clk , reset;
    wire z ;

    sq0110 DUT (x , clk , reset , z ) ;

    initial begin
        $dumpfile("sq0110.vcd") ;
        $dumpvars (0 , tb_sq0110) ;
        clk = 1'b0 ;
        reset = 1'b1 ;
        #15 reset = 1'b0 ;
        end

    initial 
        forever #5 clk = ~clk ;

    initial begin
        #12 x=0; #10 x=0; #10 x=1; #10 x=1;
        #10 x=0; #10 x=1; #10 x=1; #10 x=0;
        #10 x=0; #10 x=1; #10 x=1; #10 x=0;
        #10 $finish;
        end

endmodule

sq0110.vcd
$date
	Thu Oct 02 07:36:39 2025
$end
$version
	Icarus Verilog
$end
$timescale
	1ps
$end
$scope module tb_sq0110 $end
$var wire 1 ! z $end
$var reg 1 " clk $end
$var reg 1 # reset $end
$var reg 1 $ x $end
$scope module DUT $end
$var wire 1 " clk $end
$var wire 1 # reset $end
$var wire 1 $ x $end
$var parameter 32 % S0 $end
$var parameter 32 & S1 $end
$var parameter 32 ' S2 $end
$var parameter 32 ( S3 $end
$var reg 2 ) NS [0:1] $end
$var reg 2 * PS [0:1] $end
$var reg 1 ! z $end
$upscope $end
$upscope $end
$enddefinitions $end
$comment Show the parameter values. $end
$dumpall
b11 (
b10 '
b1 &
b0 %
$end
#0
$dumpvars
b0 *
b0x )
x$
1#
0"
0!
$end
#5000
1"
#10000
0"
#12000
b1 )
0$
#15000
b1 *
1"
0#
#20000
0"
#25000
1"
#30000
0"
#32000
b10 )
1$
#35000
b11 )
b10 *
1"
#40000
0"
#45000
b0 )
b11 *
1"
#50000
0"
#52000
b1 )
1!
0$
#55000
0!
b1 *
1"
#60000
0"
#62000
b10 )
1$
#65000
b11 )
b10 *
1"
#70000
0"
#75000
b0 )
b11 *
1"
#80000
0"
#82000
b1 )
1!
0$
#85000
0!
b1 *
1"
#90000
0"
#95000
1"
#100000
0"
#102000
b10 )
1$
#105000
b11 )
b10 *
1"
#110000
0"
#115000
b0 )
b11 *
1"
#120000
0"
#122000
b1 )
1!
0$
#125000
0!
b1 *
1"
